googlesearch/LICENSE
googlesearch/__init__.py
googlesearch/__main__.py
googlesearch/constants.py
googlesearch/exceptions.py
googlesearch/googlesearch.py
googlesearch/models.py
googlesearch/utils/__init__.py
googlesearch/utils/cleanup.py
python_googlesearch-1.1.1.dist-info/LICENSE
python_googlesearch-1.1.1.dist-info/METADATA
python_googlesearch-1.1.1.dist-info/WHEEL
python_googlesearch-1.1.1.dist-info/entry_points.txt
python_googlesearch-1.1.1.dist-info/top_level.txt
python_googlesearch-1.1.1.dist-info/RECORD
