Metadata-Version: 2.1
Name: python-googlesearch
Version: 1.1.1
Summary: This module lets you use Google Searching capabilities right from your Python code
Home-page: https://github.com/Animenosekai/googlesearch
Author: Anime no Sekai
Author-email: niichannomail@gmail.com
License: MIT License
Download-URL: https://github.com/Animenosekai/googlesearch/archive/v1.1.1.tar.gz
Keywords: python,Anime no Sekai,animenosekai,googlesearch
Platform: UNKNOWN
Classifier: Development Status :: 5 - Production/Stable
Classifier: License :: OSI Approved :: MIT License
Classifier: Programming Language :: Python :: 3
Classifier: Programming Language :: Python :: 3.2
Classifier: Programming Language :: Python :: 3.3
Classifier: Programming Language :: Python :: 3.4
Classifier: Programming Language :: Python :: 3.5
Classifier: Programming Language :: Python :: 3.6
Classifier: Programming Language :: Python :: 3.7
Classifier: Programming Language :: Python :: 3.8
Classifier: Programming Language :: Python :: 3.9
Requires-Python: >=3.2, <4
